skyun/__init__.py
skyun/client.py
skyun/common.py
skyun/constant.py
skyun/server.py
skyun/tcp_relay.py
skyun/udp_relay.py
skyun-1.1.1.dist-info/LICENSE
skyun-1.1.1.dist-info/METADATA
skyun-1.1.1.dist-info/WHEEL
skyun-1.1.1.dist-info/entry_points.txt
skyun-1.1.1.dist-info/top_level.txt
skyun-1.1.1.dist-info/RECORD
