Metadata-Version: 2.1
Name: skyun
Version: 1.1.1
Summary: A socks5 proxy software
Home-page: https://github.com/comeacrossyun/skyun
Author: Yuyun Liu (cayun/comeacrossyun)
Author-email: comeacrossyun@gmail.com
License: MIT
Platform: UNKNOWN
Classifier: License :: OSI Approved :: MIT License
Classifier: Programming Language :: Python :: 3
Classifier: Programming Language :: Python :: 3.6
Classifier: Programming Language :: Python :: 3.7
Requires-Python: >=3.6.0
